simpar/__init__.py
simpar/groups.py
simpar/micro.py
simpar/scenario.py
simpar/sim.py
simpar/strategy.py
simpar/trajectory.py
simpar/tests/__init__.py
simpar/tests/test_groups.py
simpar/tests/test_mirco.py
simpar/tests/test_scenario.py
simpar/tests/test_sim.py
simpar/tests/test_strategy.py
simpar/tests/test_trajectory.py
simpar-0.1.0.dist-info/LICENSE
simpar-0.1.0.dist-info/METADATA
simpar-0.1.0.dist-info/WHEEL
simpar-0.1.0.dist-info/top_level.txt
simpar-0.1.0.dist-info/RECORD
