Metadata-Version: 2.1
Name: simpar
Version: 0.1.0
Summary: A Python package for analyzing pandemic response measures
Home-page: https://github.com/cornell-covid-modeling/simpar
Author: Cornell Covid Modeling Team
Author-email: hwr26@cornell.edu
Classifier: Programming Language :: Python :: 3.5
Classifier: Programming Language :: Python :: 3.6
Classifier: Programming Language :: Python :: 3.7
Classifier: Programming Language :: Python :: 3.8
Classifier: Programming Language :: Python :: 3.9
Classifier: Programming Language :: Python :: 3.10
Classifier: License :: OSI Approved :: MIT License
Classifier: Operating System :: OS Independent
Requires-Python: >=3.5
License-File: LICENSE
Requires-Dist: numpy (>=1.21)
Requires-Dist: pandas (>=1.2)
Requires-Dist: matplotlib (>=3.3)
Requires-Dist: scipy (>=1.6)
Requires-Dist: pyyaml (>=5.4)
Requires-Dist: json5 (>=0.9.5)
Provides-Extra: dev
Requires-Dist: pytest (>=5) ; extra == 'dev'
Requires-Dist: mock (>=3) ; extra == 'dev'
Requires-Dist: coverage (>=4.5) ; extra == 'dev'
Requires-Dist: tox (>=3) ; extra == 'dev'
Requires-Dist: flake8 (>=3.9) ; extra == 'dev'
